{
  "config.internalLinks.units.title": "Egységek",
  "config.internalLinks.units.description": "Minden frakció egységei — statisztikák, képességek és fejlesztési utak.",
  "config.internalLinks.units.linkText": "Összes egység",
  "config.internalLinks.heroes.title": "Hősök",
  "config.internalLinks.heroes.description": "Minden hős — statisztikák, specializációk, kezdő seregek és képességek.",
  "config.internalLinks.heroes.linkText": "Összes hős",
  "config.internalLinks.spells.title": "Varázslatok",
  "config.internalLinks.spells.description": "Harci és világ varázslatok minden iskolából — Nappali, Éjszakai, Ősi, Űr és Semleges.",
  "config.internalLinks.spells.linkText": "Összes varázslat",
  "config.internalLinks.items.title": "Varázstárgyak",
  "config.internalLinks.items.description": "Minden műtárgy, felszerelés, tekercs és szett — bónuszok és fejlesztések.",
  "config.internalLinks.items.linkText": "Összes tárgy",
  "config.internalLinks.skills.title": "Képességek",
  "config.internalLinks.skills.description": "Hős képességek és al-képességek — szintek és bónuszok.",
  "config.internalLinks.skills.linkText": "Összes képesség",
  "config.internalLinks.factions.title": "Frakciók",
  "config.internalLinks.factions.description": "Frakció áttekintés — törvények, specializációk és egyedi mechanikák.",
  "config.internalLinks.factions.linkText": "Frakciók felfedezése",
  "config.internalLinks.buildings.title": "Épületek",
  "config.internalLinks.buildings.description": "Városi épületek frakciónként — költségek, előfeltételek és toborzás.",
  "config.internalLinks.buildings.linkText": "Épületek megtekintése",
  "config.internalLinks.map-objects.title": "Térképobjektumok",
  "config.internalLinks.map-objects.description": "Lakhelyek, erőforrás-helyek, kalandok, mágikus szentélyek és még több.",
  "config.internalLinks.map-objects.linkText": "Térképobjektumok",
  "config.internalLinks.maps.title": "Maps",
  "config.internalLinks.maps.description": "PvP map templates: game mode, win condition, player count, size, and schematic layout.",
  "config.internalLinks.maps.linkText": "Browse Maps",
  "config.internalLinks.mechanics.title": "Játékmechanikák",
  "config.internalLinks.mechanics.description": "Hogyan működnek a harci értékek, szerencse, morál és sebzési képletek.",
  "config.internalLinks.mechanics.linkText": "Mechanikák"
}
